the_compiler/__init__.py
the_compiler/the_compiler.py
the_compiler-0.1.7.dist-info/LICENSE
the_compiler-0.1.7.dist-info/METADATA
the_compiler-0.1.7.dist-info/WHEEL
the_compiler-0.1.7.dist-info/top_level.txt
the_compiler-0.1.7.dist-info/RECORD
