Metadata-Version: 2.1
Name: the-compiler
Version: 0.1.7
Summary: The Compiler 
Home-page: https://github.com/kyegomez/the-compiler
Author: Kye Gomez
Author-email: kye@apac.ai
License: MIT
Keywords: artificial intelligence,deep learning,optimizers,Prompt Engineering
Classifier: Development Status :: 4 - Beta
Classifier: Intended Audience :: Developers
Classifier: Topic :: Scientific/Engineering :: Artificial Intelligence
Classifier: License :: OSI Approved :: MIT License
Classifier: Programming Language :: Python :: 3.6
License-File: LICENSE
Requires-Dist: tree-of-thoughts
